{
  "header": {
    "notice": {
      "message": {
        "content": "¡Envío gratis en pedidos mayores a $50!",
        "color": "#ffffff"
      },
      "backgroundColor": "#34d399"
    },
    "logo": {
      "position": "center",
      "size": "normal",
      "image_url": "https://png.pngtree.com/png-vector/20220730/ourmid/pngtree-circle-eco-friendly-logo-symbol-png-image_6093131.png"
    },
    "navigation": {
      "links": [
        {
          "type": "section",
          "content": "Inicio",
          "href": "#hero"
        },
        {
          "type": "section",
          "content": "Productos",
          "href": "#products"
        },
        {
          "type": "section",
          "content": "Nosotros",
          "href": "#about"
        },
        {
          "type": "external",
          "content": "Blog",
          "href": "https://ecoflow.blog"
        }
      ],
      "position": "center"
    },
    "cta": [
      {
        "type": "primary",
        "content": "Comprar ahora",
        "href": "#products"
      },
      {
        "type": "secondary",
        "content": "Contacto",
        "href": "#contact"
      }
    ],
    "backgroundColor": "#fff",
    "textColor": "#111",
    "elevation": 1,
    "position": "sticky"
  },
  "hero": {
    "headline": {
      "content": "Energía limpia para un futuro sostenible"
    },
    "subheadline": {
      "content": "Descubre nuestros productos ecológicos diseñados para cuidar el planeta."
    },
    "cta": [
      {
        "type": "primary",
        "content": "Ver productos",
        "href": "#products"
      },
      {
        "type": "secondary",
        "content": "Saber más",
        "href": "#about"
      }
    ],
    "showcase": {
      "type": "image",
      "source_url": "https://i.imgur.com/42BRqfd.png",
      "position": "bottom",
      "offset_x": 0,
      "offset_y": 0,
      "scale": 2,
      "margin": {
        "top": 0,
        "bottom": 0,
        "left": 0,
        "right": 0
      },
      "padding": {
        "top": 0,
        "bottom": 0,
        "left": 0,
        "right": 0
      },
      "elevation": 0,
      "zIndex": -1,
      "fade": 1
    },
    "backgroundColor": "#f0f0f0",
    "textColor": "#333333"
  },
  "section": [
    {
      "title": {
        "content": "Nuestros productos destacados",
        "position": "left"
      },
      "description": {
        "content": "Conoce nuestras soluciones eco-amigables favoritas entre nuestros clientes."
      },
      "layout": "3-columns",
      "items": [
        {
          "title": "Panel Solar Plegable",
          "description": "Ideal para acampar o viajar, portátil y eficiente.",
          "media": {
            "type": "image",
            "source_url": "https://images.unsplash.com/photo-1509391366360-2e959784a276?auto=format&fit=crop&w=800&q=80"
          },
          "cta": {
            "type": "primary",
            "content": "Comprar",
            "href": "#"
          },
          "strategy": "simple"
        },
        {
          "title": "Botella Reutilizable",
          "description": "Diseñada para durar. Sin plásticos, sin residuos.",
          "media": {
            "type": "image",
            "source_url": "https://images.unsplash.com/photo-1589365278144-c9e705f843ba?auto=format&fit=crop&w=800&q=80"
          },
          "cta": {
            "type": "primary",
            "content": "Comprar",
            "href": "#"
          },
          "strategy": "simple"
        },
        {
          "title": "Cargador Solar USB",
          "description": "Carga tus dispositivos en cualquier parte del mundo.",
          "media": {
            "type": "image",
            "source_url": "https://images.unsplash.com/photo-1548690312-e3b507d8c110?auto=format&fit=crop&w=800&q=80"
          },
          "cta": {
            "type": "primary",
            "content": "Comprar",
            "href": "#"
          },
          "strategy": "simple"
        }
      ],
      "backgroundColor": "#f0f0f0",
      "textColor": "#333333"
    },
    {
      "title": {
        "content": "¿Quiénes somos?",
        "position": "left"
      },
      "description": {
        "content": "EcoFlow es una empresa comprometida con el medio ambiente. Creamos productos que combinan diseño, funcionalidad y responsabilidad ecológica."
      },
      "layout": "1-column",
      "items": [
        {
          "title": "Nuestro compromiso",
          "description": "Trabajamos con materiales reciclados y procesos sustentables para reducir nuestra huella ecológica.",
          "media": {
            "type": "image",
            "source_url": "https://images.unsplash.com/photo-1603321268596-e5c8bba1e723?auto=format&fit=crop&w=800&q=80"
          },
          "cta": {
            "type": "non-primary",
            "content": "Leer más",
            "href": "#"
          }
        }
      ],
      "backgroundColor": "#f0f0f0",
      "textColor": "#333333"
    }
  ],
  "footer": {
    "layout": "logo-left",
    "logo": {
      "image_url": "https://images.unsplash.com/photo-1509021436665-8f07dbf5bf1d?auto=format&fit=crop&w=80&q=80",
      "email": "hola@ecoflow.com",
      "social": [
        {
          "platform": "facebook",
          "url": "https://facebook.com/ecoflow"
        },
        {
          "platform": "instagram",
          "url": "https://instagram.com/ecoflow"
        },
        {
          "platform": "twitter",
          "url": "https://twitter.com/ecoflow"
        }
      ]
    },
    "columns": [
      {
        "title": "Empresa",
        "links": [
          {
            "content": "Sobre nosotros",
            "href": "#about"
          },
          {
            "content": "Carreras",
            "href": "#"
          }
        ]
      },
      {
        "title": "Ayuda",
        "links": [
          {
            "content": "Preguntas frecuentes",
            "href": "#"
          },
          {
            "content": "Contacto",
            "href": "#contact"
          }
        ]
      },
      {
        "title": "Legal",
        "links": [
          {
            "content": "Términos y condiciones",
            "href": "#"
          },
          {
            "content": "Política de privacidad",
            "href": "#"
          }
        ]
      }
    ],
    "backgroundColor": "#f3f4f6",
    "textColor": "#111827"
  },
  "palette": {
    "primary": "#34d399",
    "secondary": "#10b981",
    "accent": "#047857",
    "background": "#fff",
    "text": "#111827"
  }
}
